{
  "address": "Ad6HcceZRDnvSTcksUDrUEdnxuuF8HQDvr5Ru1YZscMN",
  "metadata": {
    "name": "create_token",
    "version": "0.1.0",
    "spec": "0.1.0",
    "description": "create_token"
  },
  "instructions": [
    {
      "name": "create_token",
      "discriminator": [
        84,
        52,
        204,
        228,
        24,
        140,
        234,
        75
      ],
      "accounts": [
        {
          "name": "signer",
          "writable": true,
          "signer": true
        },
        {
          "name": "mint",
          "writable": true,
          "pda": {
            "seeds": [
              {
                "kind": "const",
                "value": [
                  106,
                  111,
                  104,
                  110,
                  121,
                  95,
                  109,
                  105,
                  110,
                  116
                ]
              },
              {
                "kind": "account",
                "path": "signer"
              }
            ]
          }
        },
        {
          "name": "token_account",
          "writable": true,
          "pda": {
            "seeds": [
              {
                "kind": "account",
                "path": "signer"
              },
              {
                "kind": "account",
                "path": "token_program"
              },
              {
                "kind": "account",
                "path": "mint"
              }
            ],
            "program": {
              "kind": "const",
              "value": [
                140,
                151,
                37,
                143,
                78,
                36,
                137,
                241,
                187,
                61,
                16,
                41,
                20,
                142,
                13,
                131,
                11,
                90,
                19,
                153,
                218,
                255,
                16,
                132,
                4,
                142,
                123,
                216,
                219,
                233,
                248,
                89
              ]
            }
          }
        },
        {
          "name": "metadata",
          "writable": true,
          "pda": {
            "seeds": [
              {
                "kind": "const",
                "value": [
                  109,
                  101,
                  116,
                  97,
                  100,
                  97,
                  116,
                  97
                ]
              },
              {
                "kind": "account",
                "path": "token_metadata_program"
              },
              {
                "kind": "account",
                "path": "mint"
              }
            ],
            "program": {
              "kind": "account",
              "path": "token_metadata_program"
            }
          }
        },
        {
          "name": "token_metadata_program",
          "address": "metaqbxxUerdq28cj1RbAWkYQm3ybzjb6a8bt518x1s"
        },
        {
          "name": "associated_token_program",
          "address": "ATokenGPvbdGVxr1b2hvZbsiqW5xWH25efTNsLJA8knL"
        },
        {
          "name": "token_program"
        },
        {
          "name": "rent",
          "address": "SysvarRent111111111111111111111111111111111"
        },
        {
          "name": "system_program",
          "address": "11111111111111111111111111111111"
        }
      ],
      "args": [
        {
          "name": "name",
          "type": "string"
        },
        {
          "name": "symbol",
          "type": "string"
        },
        {
          "name": "uri",
          "type": "string"
        },
        {
          "name": "amount",
          "type": "u64"
        }
      ]
    }
  ]
}